eternity/__init__.py
eternity/__main__.py
eternity/database.py
eternity/main.py
eternity/models.py
eternity/static/style.css
eternity/templates/index.html
eternity_mcp-0.1.1.dist-info/METADATA
eternity_mcp-0.1.1.dist-info/WHEEL
eternity_mcp-0.1.1.dist-info/entry_points.txt
eternity_mcp-0.1.1.dist-info/licenses/LICENSE
eternity_mcp-0.1.1.dist-info/RECORD
