Metadata-Version: 2.4
Name: eternity-mcp
Version: 0.1.1
Summary: Your eternal second brain, running locally. Private, fast, and built for AI agents that actually remember.
License: MIT License
License-File: LICENSE
Author: Junior Dantas
Author-email: juniordante01@gmail.com
Requires-Python: >=3.12
Classifier: Programming Language :: Python :: 3
Classifier: License :: OSI Approved :: MIT License
Classifier: Operating System :: OS Independent
Classifier: Topic :: Scientific/Engineering :: Artificial Intelligence
Requires-Dist: chromadb
Requires-Dist: fastapi
Requires-Dist: jinja2
Requires-Dist: pypdf
Requires-Dist: python-multipart
Requires-Dist: requests
Requires-Dist: sentence-transformers
Requires-Dist: uvicorn[standard]
